imsize/#consoleapp.py#
imsize/__init__.py
imsize/argv.py
imsize/consoleapp.py
imsize/exrhdr.py
imsize/imsize.py
imsize/pfmhdr.py
imsize/pnmhdr.py
imsize/version.py
imsize-1.9.1.dist-info/METADATA
imsize-1.9.1.dist-info/WHEEL
imsize-1.9.1.dist-info/entry_points.txt
imsize-1.9.1.dist-info/licenses/LICENSE
imsize-1.9.1.dist-info/RECORD
