Metadata-Version: 2.4
Name: imsize
Version: 1.9.1
Summary: Lightning-fast extraction of basic image metadata
Project-URL: Homepage, http://github.com/toaarnio/imsize
Author-email: Tomi Aarnio <tomi.p.aarnio@gmail.com>
License-File: LICENSE
Classifier: License :: OSI Approved :: MIT License
Classifier: Operating System :: OS Independent
Classifier: Programming Language :: Python :: 3
Requires-Python: >=3.10
Requires-Dist: numpy>=2.2.0
Requires-Dist: pyexiftool>=0.5.6
Requires-Dist: pyexiv2>=2.15.0
Requires-Dist: rawpy>=0.25.0
Requires-Dist: sympy>=1.14.0
